<?xml version="1.0" encoding="UTF-8"?>
<issues format="6" by="lint 8.4.0-alpha01" type="baseline" client="" dependencies="true" name="" variant="all" version="8.4.0-alpha01">

    <issue
        id="NewApi"
        message="Call requires API level 31 (current min is 30): `libcore.io.IoUtils#close`"
        errorLine1="            IoUtils.close(mSocket);"
        errorLine2="                    ~~~~~">
        <location
            file="packages/modules/IPsec/src/java/com/android/internal/net/ipsec/ike/IkeUdpSocket.java"
            line="121"
            column="21"/>
    </issue>

    <issue
        id="FlaggedApi"
        message="@FlaggedApi should specify an actual flag constant; raw strings are discouraged (and more importantly, **not enforced**)"
        errorLine1="    @FlaggedApi(&quot;com.android.ipsec.flags.liveness_check_api&quot;)"
        errorLine2="                ~~~~~~~~~~~~~~~~~~~~~~~~~~~~~~~~~~~~~~~~~~~~">
        <location
            file="packages/modules/IPsec/src/java/android/net/ipsec/ike/IkeSession.java"
            line="461"
            column="17"/>
    </issue>

    <issue
        id="FlaggedApi"
        message="@FlaggedApi should specify an actual flag constant; raw strings are discouraged (and more importantly, **not enforced**)"
        errorLine1="    @FlaggedApi(&quot;com.android.ipsec.flags.dumpsys_api&quot;)"
        errorLine2="                ~~~~~~~~~~~~~~~~~~~~~~~~~~~~~~~~~~~~~">
        <location
            file="packages/modules/IPsec/src/java/android/net/ipsec/ike/IkeSession.java"
            line="471"
            column="17"/>
    </issue>

    <issue
        id="FlaggedApi"
        message="@FlaggedApi should specify an actual flag constant; raw strings are discouraged (and more importantly, **not enforced**)"
        errorLine1="    @FlaggedApi(&quot;com.android.ipsec.flags.liveness_check_api&quot;)"
        errorLine2="                ~~~~~~~~~~~~~~~~~~~~~~~~~~~~~~~~~~~~~~~~~~~~">
        <location
            file="packages/modules/IPsec/src/java/android/net/ipsec/ike/IkeSessionCallback.java"
            line="52"
            column="17"/>
    </issue>

    <issue
        id="FlaggedApi"
        message="@FlaggedApi should specify an actual flag constant; raw strings are discouraged (and more importantly, **not enforced**)"
        errorLine1="    @FlaggedApi(&quot;com.android.ipsec.flags.liveness_check_api&quot;)"
        errorLine2="                ~~~~~~~~~~~~~~~~~~~~~~~~~~~~~~~~~~~~~~~~~~~~">
        <location
            file="packages/modules/IPsec/src/java/android/net/ipsec/ike/IkeSessionCallback.java"
            line="52"
            column="17"/>
    </issue>

    <issue
        id="FlaggedApi"
        message="@FlaggedApi should specify an actual flag constant; raw strings are discouraged (and more importantly, **not enforced**)"
        errorLine1="    @FlaggedApi(&quot;com.android.ipsec.flags.liveness_check_api&quot;)"
        errorLine2="                ~~~~~~~~~~~~~~~~~~~~~~~~~~~~~~~~~~~~~~~~~~~~">
        <location
            file="packages/modules/IPsec/src/java/android/net/ipsec/ike/IkeSessionCallback.java"
            line="52"
            column="17"/>
    </issue>

    <issue
        id="FlaggedApi"
        message="@FlaggedApi should specify an actual flag constant; raw strings are discouraged (and more importantly, **not enforced**)"
        errorLine1="    @FlaggedApi(&quot;com.android.ipsec.flags.liveness_check_api&quot;)"
        errorLine2="                ~~~~~~~~~~~~~~~~~~~~~~~~~~~~~~~~~~~~~~~~~~~~">
        <location
            file="packages/modules/IPsec/src/java/android/net/ipsec/ike/IkeSessionCallback.java"
            line="52"
            column="17"/>
    </issue>

    <issue
        id="FlaggedApi"
        message="@FlaggedApi should specify an actual flag constant; raw strings are discouraged (and more importantly, **not enforced**)"
        errorLine1="    @FlaggedApi(&quot;com.android.ipsec.flags.liveness_check_api&quot;)"
        errorLine2="                ~~~~~~~~~~~~~~~~~~~~~~~~~~~~~~~~~~~~~~~~~~~~">
        <location
            file="packages/modules/IPsec/src/java/android/net/ipsec/ike/IkeSessionCallback.java"
            line="62"
            column="17"/>
    </issue>

    <issue
        id="FlaggedApi"
        message="@FlaggedApi should specify an actual flag constant; raw strings are discouraged (and more importantly, **not enforced**)"
        errorLine1="    @FlaggedApi(&quot;com.android.ipsec.flags.liveness_check_api&quot;)"
        errorLine2="                ~~~~~~~~~~~~~~~~~~~~~~~~~~~~~~~~~~~~~~~~~~~~">
        <location
            file="packages/modules/IPsec/src/java/android/net/ipsec/ike/IkeSessionCallback.java"
            line="62"
            column="17"/>
    </issue>

    <issue
        id="FlaggedApi"
        message="@FlaggedApi should specify an actual flag constant; raw strings are discouraged (and more importantly, **not enforced**)"
        errorLine1="    @FlaggedApi(&quot;com.android.ipsec.flags.liveness_check_api&quot;)"
        errorLine2="                ~~~~~~~~~~~~~~~~~~~~~~~~~~~~~~~~~~~~~~~~~~~~">
        <location
            file="packages/modules/IPsec/src/java/android/net/ipsec/ike/IkeSessionCallback.java"
            line="62"
            column="17"/>
    </issue>

    <issue
        id="FlaggedApi"
        message="@FlaggedApi should specify an actual flag constant; raw strings are discouraged (and more importantly, **not enforced**)"
        errorLine1="    @FlaggedApi(&quot;com.android.ipsec.flags.liveness_check_api&quot;)"
        errorLine2="                ~~~~~~~~~~~~~~~~~~~~~~~~~~~~~~~~~~~~~~~~~~~~">
        <location
            file="packages/modules/IPsec/src/java/android/net/ipsec/ike/IkeSessionCallback.java"
            line="62"
            column="17"/>
    </issue>

    <issue
        id="FlaggedApi"
        message="@FlaggedApi should specify an actual flag constant; raw strings are discouraged (and more importantly, **not enforced**)"
        errorLine1="    @FlaggedApi(&quot;com.android.ipsec.flags.liveness_check_api&quot;)"
        errorLine2="                ~~~~~~~~~~~~~~~~~~~~~~~~~~~~~~~~~~~~~~~~~~~~">
        <location
            file="packages/modules/IPsec/src/java/android/net/ipsec/ike/IkeSessionCallback.java"
            line="72"
            column="17"/>
    </issue>

    <issue
        id="FlaggedApi"
        message="@FlaggedApi should specify an actual flag constant; raw strings are discouraged (and more importantly, **not enforced**)"
        errorLine1="    @FlaggedApi(&quot;com.android.ipsec.flags.liveness_check_api&quot;)"
        errorLine2="                ~~~~~~~~~~~~~~~~~~~~~~~~~~~~~~~~~~~~~~~~~~~~">
        <location
            file="packages/modules/IPsec/src/java/android/net/ipsec/ike/IkeSessionCallback.java"
            line="72"
            column="17"/>
    </issue>

    <issue
        id="FlaggedApi"
        message="@FlaggedApi should specify an actual flag constant; raw strings are discouraged (and more importantly, **not enforced**)"
        errorLine1="    @FlaggedApi(&quot;com.android.ipsec.flags.liveness_check_api&quot;)"
        errorLine2="                ~~~~~~~~~~~~~~~~~~~~~~~~~~~~~~~~~~~~~~~~~~~~">
        <location
            file="packages/modules/IPsec/src/java/android/net/ipsec/ike/IkeSessionCallback.java"
            line="72"
            column="17"/>
    </issue>

    <issue
        id="FlaggedApi"
        message="@FlaggedApi should specify an actual flag constant; raw strings are discouraged (and more importantly, **not enforced**)"
        errorLine1="    @FlaggedApi(&quot;com.android.ipsec.flags.liveness_check_api&quot;)"
        errorLine2="                ~~~~~~~~~~~~~~~~~~~~~~~~~~~~~~~~~~~~~~~~~~~~">
        <location
            file="packages/modules/IPsec/src/java/android/net/ipsec/ike/IkeSessionCallback.java"
            line="72"
            column="17"/>
    </issue>

    <issue
        id="FlaggedApi"
        message="@FlaggedApi should specify an actual flag constant; raw strings are discouraged (and more importantly, **not enforced**)"
        errorLine1="    @FlaggedApi(&quot;com.android.ipsec.flags.liveness_check_api&quot;)"
        errorLine2="                ~~~~~~~~~~~~~~~~~~~~~~~~~~~~~~~~~~~~~~~~~~~~">
        <location
            file="packages/modules/IPsec/src/java/android/net/ipsec/ike/IkeSessionCallback.java"
            line="82"
            column="17"/>
    </issue>

    <issue
        id="FlaggedApi"
        message="@FlaggedApi should specify an actual flag constant; raw strings are discouraged (and more importantly, **not enforced**)"
        errorLine1="    @FlaggedApi(&quot;com.android.ipsec.flags.liveness_check_api&quot;)"
        errorLine2="                ~~~~~~~~~~~~~~~~~~~~~~~~~~~~~~~~~~~~~~~~~~~~">
        <location
            file="packages/modules/IPsec/src/java/android/net/ipsec/ike/IkeSessionCallback.java"
            line="82"
            column="17"/>
    </issue>

    <issue
        id="FlaggedApi"
        message="@FlaggedApi should specify an actual flag constant; raw strings are discouraged (and more importantly, **not enforced**)"
        errorLine1="    @FlaggedApi(&quot;com.android.ipsec.flags.liveness_check_api&quot;)"
        errorLine2="                ~~~~~~~~~~~~~~~~~~~~~~~~~~~~~~~~~~~~~~~~~~~~">
        <location
            file="packages/modules/IPsec/src/java/android/net/ipsec/ike/IkeSessionCallback.java"
            line="82"
            column="17"/>
    </issue>

    <issue
        id="FlaggedApi"
        message="@FlaggedApi should specify an actual flag constant; raw strings are discouraged (and more importantly, **not enforced**)"
        errorLine1="    @FlaggedApi(&quot;com.android.ipsec.flags.liveness_check_api&quot;)"
        errorLine2="                ~~~~~~~~~~~~~~~~~~~~~~~~~~~~~~~~~~~~~~~~~~~~">
        <location
            file="packages/modules/IPsec/src/java/android/net/ipsec/ike/IkeSessionCallback.java"
            line="82"
            column="17"/>
    </issue>

    <issue
        id="FlaggedApi"
        message="@FlaggedApi should specify an actual flag constant; raw strings are discouraged (and more importantly, **not enforced**)"
        errorLine1="    @FlaggedApi(&quot;com.android.ipsec.flags.liveness_check_api&quot;)"
        errorLine2="                ~~~~~~~~~~~~~~~~~~~~~~~~~~~~~~~~~~~~~~~~~~~~">
        <location
            file="packages/modules/IPsec/src/java/android/net/ipsec/ike/IkeSessionCallback.java"
            line="94"
            column="17"/>
    </issue>

    <issue
        id="FlaggedApi"
        message="@FlaggedApi should specify an actual flag constant; raw strings are discouraged (and more importantly, **not enforced**)"
        errorLine1="    @FlaggedApi(&quot;com.android.ipsec.flags.liveness_check_api&quot;)"
        errorLine2="                ~~~~~~~~~~~~~~~~~~~~~~~~~~~~~~~~~~~~~~~~~~~~">
        <location
            file="packages/modules/IPsec/src/java/android/net/ipsec/ike/IkeSessionCallback.java"
            line="94"
            column="17"/>
    </issue>

    <issue
        id="FlaggedApi"
        message="@FlaggedApi should specify an actual flag constant; raw strings are discouraged (and more importantly, **not enforced**)"
        errorLine1="    @FlaggedApi(&quot;com.android.ipsec.flags.liveness_check_api&quot;)"
        errorLine2="                ~~~~~~~~~~~~~~~~~~~~~~~~~~~~~~~~~~~~~~~~~~~~">
        <location
            file="packages/modules/IPsec/src/java/android/net/ipsec/ike/IkeSessionCallback.java"
            line="94"
            column="17"/>
    </issue>

    <issue
        id="FlaggedApi"
        message="@FlaggedApi should specify an actual flag constant; raw strings are discouraged (and more importantly, **not enforced**)"
        errorLine1="    @FlaggedApi(&quot;com.android.ipsec.flags.liveness_check_api&quot;)"
        errorLine2="                ~~~~~~~~~~~~~~~~~~~~~~~~~~~~~~~~~~~~~~~~~~~~">
        <location
            file="packages/modules/IPsec/src/java/android/net/ipsec/ike/IkeSessionCallback.java"
            line="94"
            column="17"/>
    </issue>

    <issue
        id="FlaggedApi"
        message="@FlaggedApi should specify an actual flag constant; raw strings are discouraged (and more importantly, **not enforced**)"
        errorLine1="    @FlaggedApi(&quot;com.android.ipsec.flags.liveness_check_api&quot;)"
        errorLine2="                ~~~~~~~~~~~~~~~~~~~~~~~~~~~~~~~~~~~~~~~~~~~~">
        <location
            file="packages/modules/IPsec/src/java/android/net/ipsec/ike/IkeSessionCallback.java"
            line="111"
            column="17"/>
    </issue>

    <issue
        id="FlaggedApi"
        message="@FlaggedApi should specify an actual flag constant; raw strings are discouraged (and more importantly, **not enforced**)"
        errorLine1="    @FlaggedApi(&quot;com.android.ipsec.flags.liveness_check_api&quot;)"
        errorLine2="                ~~~~~~~~~~~~~~~~~~~~~~~~~~~~~~~~~~~~~~~~~~~~">
        <location
            file="packages/modules/IPsec/src/java/android/net/ipsec/ike/IkeSessionCallback.java"
            line="111"
            column="17"/>
    </issue>

    <issue
        id="FlaggedApi"
        message="@FlaggedApi should specify an actual flag constant; raw strings are discouraged (and more importantly, **not enforced**)"
        errorLine1="    @FlaggedApi(&quot;com.android.ipsec.flags.liveness_check_api&quot;)"
        errorLine2="                ~~~~~~~~~~~~~~~~~~~~~~~~~~~~~~~~~~~~~~~~~~~~">
        <location
            file="packages/modules/IPsec/src/java/android/net/ipsec/ike/IkeSessionCallback.java"
            line="111"
            column="17"/>
    </issue>

    <issue
        id="FlaggedApi"
        message="@FlaggedApi should specify an actual flag constant; raw strings are discouraged (and more importantly, **not enforced**)"
        errorLine1="    @FlaggedApi(&quot;com.android.ipsec.flags.liveness_check_api&quot;)"
        errorLine2="                ~~~~~~~~~~~~~~~~~~~~~~~~~~~~~~~~~~~~~~~~~~~~">
        <location
            file="packages/modules/IPsec/src/java/android/net/ipsec/ike/IkeSessionCallback.java"
            line="111"
            column="17"/>
    </issue>

    <issue
        id="FlaggedApi"
        message="@FlaggedApi should specify an actual flag constant; raw strings are discouraged (and more importantly, **not enforced**)"
        errorLine1="    @FlaggedApi(&quot;com.android.ipsec.flags.liveness_check_api&quot;)"
        errorLine2="                ~~~~~~~~~~~~~~~~~~~~~~~~~~~~~~~~~~~~~~~~~~~~">
        <location
            file="packages/modules/IPsec/src/java/android/net/ipsec/ike/IkeSessionCallback.java"
            line="325"
            column="17"/>
    </issue>

    <issue
        id="FlaggedApi"
        message="@FlaggedApi should specify an actual flag constant; raw strings are discouraged (and more importantly, **not enforced**)"
        errorLine1="    @FlaggedApi(&quot;com.android.ipsec.flags.liveness_check_api&quot;)"
        errorLine2="                ~~~~~~~~~~~~~~~~~~~~~~~~~~~~~~~~~~~~~~~~~~~~">
        <location
            file="packages/modules/IPsec/src/java/android/net/ipsec/ike/IkeSessionCallback.java"
            line="325"
            column="17"/>
    </issue>

    <issue
        id="FlaggedApi"
        message="@FlaggedApi should specify an actual flag constant; raw strings are discouraged (and more importantly, **not enforced**)"
        errorLine1="    @FlaggedApi(&quot;com.android.ipsec.flags.dpd_disable_api&quot;)"
        errorLine2="                ~~~~~~~~~~~~~~~~~~~~~~~~~~~~~~~~~~~~~~~~~">
        <location
            file="packages/modules/IPsec/src/java/android/net/ipsec/ike/IkeSessionParams.java"
            line="373"
            column="17"/>
    </issue>

    <issue
        id="FlaggedApi"
        message="@FlaggedApi should specify an actual flag constant; raw strings are discouraged (and more importantly, **not enforced**)"
        errorLine1="    @FlaggedApi(&quot;com.android.ipsec.flags.dpd_disable_api&quot;)"
        errorLine2="                ~~~~~~~~~~~~~~~~~~~~~~~~~~~~~~~~~~~~~~~~~">
        <location
            file="packages/modules/IPsec/src/java/android/net/ipsec/ike/IkeSessionParams.java"
            line="373"
            column="17"/>
    </issue>

    <issue
        id="FlaggedApi"
        message="@FlaggedApi should specify an actual flag constant; raw strings are discouraged (and more importantly, **not enforced**)"
        errorLine1="    @FlaggedApi(&quot;com.android.ipsec.flags.liveness_check_api&quot;)"
        errorLine2="                ~~~~~~~~~~~~~~~~~~~~~~~~~~~~~~~~~~~~~~~~~~~~">
        <location
            file="packages/modules/IPsec/src/java/android/net/ipsec/ike/IkeSessionParams.java"
            line="876"
            column="17"/>
    </issue>

    <issue
        id="FlaggedApi"
        message="@FlaggedApi should specify an actual flag constant; raw strings are discouraged (and more importantly, **not enforced**)"
        errorLine1="    @FlaggedApi(&quot;com.android.ipsec.flags.liveness_check_api&quot;)"
        errorLine2="                ~~~~~~~~~~~~~~~~~~~~~~~~~~~~~~~~~~~~~~~~~~~~">
        <location
            file="packages/modules/IPsec/src/java/android/net/ipsec/ike/IkeSessionParams.java"
            line="876"
            column="17"/>
    </issue>

    <issue
        id="FlaggedApi"
        message="@FlaggedApi should specify an actual flag constant; raw strings are discouraged (and more importantly, **not enforced**)"
        errorLine1="    @FlaggedApi(&quot;com.android.ipsec.flags.enabled_ike_options_api&quot;)"
        errorLine2="                ~~~~~~~~~~~~~~~~~~~~~~~~~~~~~~~~~~~~~~~~~~~~~~~~~">
        <location
            file="packages/modules/IPsec/src/java/android/net/ipsec/ike/IkeSessionParams.java"
            line="914"
            column="17"/>
    </issue>

    <issue
        id="FlaggedApi"
        message="@FlaggedApi should specify an actual flag constant; raw strings are discouraged (and more importantly, **not enforced**)"
        errorLine1="        @FlaggedApi(&quot;com.android.ipsec.flags.liveness_check_api&quot;)"
        errorLine2="                    ~~~~~~~~~~~~~~~~~~~~~~~~~~~~~~~~~~~~~~~~~~~~">
        <location
            file="packages/modules/IPsec/src/java/android/net/ipsec/ike/IkeSessionParams.java"
            line="2185"
            column="21"/>
    </issue>

    <issue
        id="FlaggedApi"
        message="@FlaggedApi should specify an actual flag constant; raw strings are discouraged (and more importantly, **not enforced**)"
        errorLine1="        @FlaggedApi(&quot;com.android.ipsec.flags.liveness_check_api&quot;)"
        errorLine2="                    ~~~~~~~~~~~~~~~~~~~~~~~~~~~~~~~~~~~~~~~~~~~~">
        <location
            file="packages/modules/IPsec/src/java/android/net/ipsec/ike/IkeSessionParams.java"
            line="2185"
            column="21"/>
    </issue>

    <issue
        id="FlaggedApi"
        message="@FlaggedApi should specify an actual flag constant; raw strings are discouraged (and more importantly, **not enforced**)"
        errorLine1="    @FlaggedApi(&quot;com.android.ipsec.flags.liveness_check_api&quot;)"
        errorLine2="                ~~~~~~~~~~~~~~~~~~~~~~~~~~~~~~~~~~~~~~~~~~~~">
        <location
            file="packages/modules/IPsec/src/java/android/net/ipsec/ike/IkeSession.java"
            line="461"
            column="17"/>
    </issue>

    <issue
        id="FlaggedApi"
        message="@FlaggedApi should specify an actual flag constant; raw strings are discouraged (and more importantly, **not enforced**)"
        errorLine1="    @FlaggedApi(&quot;com.android.ipsec.flags.dumpsys_api&quot;)"
        errorLine2="                ~~~~~~~~~~~~~~~~~~~~~~~~~~~~~~~~~~~~~">
        <location
            file="packages/modules/IPsec/src/java/android/net/ipsec/ike/IkeSession.java"
            line="471"
            column="17"/>
    </issue>

    <issue
        id="FlaggedApi"
        message="@FlaggedApi should specify an actual flag constant; raw strings are discouraged (and more importantly, **not enforced**)"
        errorLine1="    @FlaggedApi(&quot;com.android.ipsec.flags.liveness_check_api&quot;)"
        errorLine2="                ~~~~~~~~~~~~~~~~~~~~~~~~~~~~~~~~~~~~~~~~~~~~">
        <location
            file="packages/modules/IPsec/src/java/android/net/ipsec/ike/IkeSessionCallback.java"
            line="52"
            column="17"/>
    </issue>

    <issue
        id="FlaggedApi"
        message="@FlaggedApi should specify an actual flag constant; raw strings are discouraged (and more importantly, **not enforced**)"
        errorLine1="    @FlaggedApi(&quot;com.android.ipsec.flags.liveness_check_api&quot;)"
        errorLine2="                ~~~~~~~~~~~~~~~~~~~~~~~~~~~~~~~~~~~~~~~~~~~~">
        <location
            file="packages/modules/IPsec/src/java/android/net/ipsec/ike/IkeSessionCallback.java"
            line="52"
            column="17"/>
    </issue>

    <issue
        id="FlaggedApi"
        message="@FlaggedApi should specify an actual flag constant; raw strings are discouraged (and more importantly, **not enforced**)"
        errorLine1="    @FlaggedApi(&quot;com.android.ipsec.flags.liveness_check_api&quot;)"
        errorLine2="                ~~~~~~~~~~~~~~~~~~~~~~~~~~~~~~~~~~~~~~~~~~~~">
        <location
            file="packages/modules/IPsec/src/java/android/net/ipsec/ike/IkeSessionCallback.java"
            line="52"
            column="17"/>
    </issue>

    <issue
        id="FlaggedApi"
        message="@FlaggedApi should specify an actual flag constant; raw strings are discouraged (and more importantly, **not enforced**)"
        errorLine1="    @FlaggedApi(&quot;com.android.ipsec.flags.liveness_check_api&quot;)"
        errorLine2="                ~~~~~~~~~~~~~~~~~~~~~~~~~~~~~~~~~~~~~~~~~~~~">
        <location
            file="packages/modules/IPsec/src/java/android/net/ipsec/ike/IkeSessionCallback.java"
            line="52"
            column="17"/>
    </issue>

    <issue
        id="FlaggedApi"
        message="@FlaggedApi should specify an actual flag constant; raw strings are discouraged (and more importantly, **not enforced**)"
        errorLine1="    @FlaggedApi(&quot;com.android.ipsec.flags.liveness_check_api&quot;)"
        errorLine2="                ~~~~~~~~~~~~~~~~~~~~~~~~~~~~~~~~~~~~~~~~~~~~">
        <location
            file="packages/modules/IPsec/src/java/android/net/ipsec/ike/IkeSessionCallback.java"
            line="62"
            column="17"/>
    </issue>

    <issue
        id="FlaggedApi"
        message="@FlaggedApi should specify an actual flag constant; raw strings are discouraged (and more importantly, **not enforced**)"
        errorLine1="    @FlaggedApi(&quot;com.android.ipsec.flags.liveness_check_api&quot;)"
        errorLine2="                ~~~~~~~~~~~~~~~~~~~~~~~~~~~~~~~~~~~~~~~~~~~~">
        <location
            file="packages/modules/IPsec/src/java/android/net/ipsec/ike/IkeSessionCallback.java"
            line="62"
            column="17"/>
    </issue>

    <issue
        id="FlaggedApi"
        message="@FlaggedApi should specify an actual flag constant; raw strings are discouraged (and more importantly, **not enforced**)"
        errorLine1="    @FlaggedApi(&quot;com.android.ipsec.flags.liveness_check_api&quot;)"
        errorLine2="                ~~~~~~~~~~~~~~~~~~~~~~~~~~~~~~~~~~~~~~~~~~~~">
        <location
            file="packages/modules/IPsec/src/java/android/net/ipsec/ike/IkeSessionCallback.java"
            line="62"
            column="17"/>
    </issue>

    <issue
        id="FlaggedApi"
        message="@FlaggedApi should specify an actual flag constant; raw strings are discouraged (and more importantly, **not enforced**)"
        errorLine1="    @FlaggedApi(&quot;com.android.ipsec.flags.liveness_check_api&quot;)"
        errorLine2="                ~~~~~~~~~~~~~~~~~~~~~~~~~~~~~~~~~~~~~~~~~~~~">
        <location
            file="packages/modules/IPsec/src/java/android/net/ipsec/ike/IkeSessionCallback.java"
            line="62"
            column="17"/>
    </issue>

    <issue
        id="FlaggedApi"
        message="@FlaggedApi should specify an actual flag constant; raw strings are discouraged (and more importantly, **not enforced**)"
        errorLine1="    @FlaggedApi(&quot;com.android.ipsec.flags.liveness_check_api&quot;)"
        errorLine2="                ~~~~~~~~~~~~~~~~~~~~~~~~~~~~~~~~~~~~~~~~~~~~">
        <location
            file="packages/modules/IPsec/src/java/android/net/ipsec/ike/IkeSessionCallback.java"
            line="72"
            column="17"/>
    </issue>

    <issue
        id="FlaggedApi"
        message="@FlaggedApi should specify an actual flag constant; raw strings are discouraged (and more importantly, **not enforced**)"
        errorLine1="    @FlaggedApi(&quot;com.android.ipsec.flags.liveness_check_api&quot;)"
        errorLine2="                ~~~~~~~~~~~~~~~~~~~~~~~~~~~~~~~~~~~~~~~~~~~~">
        <location
            file="packages/modules/IPsec/src/java/android/net/ipsec/ike/IkeSessionCallback.java"
            line="72"
            column="17"/>
    </issue>

    <issue
        id="FlaggedApi"
        message="@FlaggedApi should specify an actual flag constant; raw strings are discouraged (and more importantly, **not enforced**)"
        errorLine1="    @FlaggedApi(&quot;com.android.ipsec.flags.liveness_check_api&quot;)"
        errorLine2="                ~~~~~~~~~~~~~~~~~~~~~~~~~~~~~~~~~~~~~~~~~~~~">
        <location
            file="packages/modules/IPsec/src/java/android/net/ipsec/ike/IkeSessionCallback.java"
            line="72"
            column="17"/>
    </issue>

    <issue
        id="FlaggedApi"
        message="@FlaggedApi should specify an actual flag constant; raw strings are discouraged (and more importantly, **not enforced**)"
        errorLine1="    @FlaggedApi(&quot;com.android.ipsec.flags.liveness_check_api&quot;)"
        errorLine2="                ~~~~~~~~~~~~~~~~~~~~~~~~~~~~~~~~~~~~~~~~~~~~">
        <location
            file="packages/modules/IPsec/src/java/android/net/ipsec/ike/IkeSessionCallback.java"
            line="72"
            column="17"/>
    </issue>

    <issue
        id="FlaggedApi"
        message="@FlaggedApi should specify an actual flag constant; raw strings are discouraged (and more importantly, **not enforced**)"
        errorLine1="    @FlaggedApi(&quot;com.android.ipsec.flags.liveness_check_api&quot;)"
        errorLine2="                ~~~~~~~~~~~~~~~~~~~~~~~~~~~~~~~~~~~~~~~~~~~~">
        <location
            file="packages/modules/IPsec/src/java/android/net/ipsec/ike/IkeSessionCallback.java"
            line="82"
            column="17"/>
    </issue>

    <issue
        id="FlaggedApi"
        message="@FlaggedApi should specify an actual flag constant; raw strings are discouraged (and more importantly, **not enforced**)"
        errorLine1="    @FlaggedApi(&quot;com.android.ipsec.flags.liveness_check_api&quot;)"
        errorLine2="                ~~~~~~~~~~~~~~~~~~~~~~~~~~~~~~~~~~~~~~~~~~~~">
        <location
            file="packages/modules/IPsec/src/java/android/net/ipsec/ike/IkeSessionCallback.java"
            line="82"
            column="17"/>
    </issue>

    <issue
        id="FlaggedApi"
        message="@FlaggedApi should specify an actual flag constant; raw strings are discouraged (and more importantly, **not enforced**)"
        errorLine1="    @FlaggedApi(&quot;com.android.ipsec.flags.liveness_check_api&quot;)"
        errorLine2="                ~~~~~~~~~~~~~~~~~~~~~~~~~~~~~~~~~~~~~~~~~~~~">
        <location
            file="packages/modules/IPsec/src/java/android/net/ipsec/ike/IkeSessionCallback.java"
            line="82"
            column="17"/>
    </issue>

    <issue
        id="FlaggedApi"
        message="@FlaggedApi should specify an actual flag constant; raw strings are discouraged (and more importantly, **not enforced**)"
        errorLine1="    @FlaggedApi(&quot;com.android.ipsec.flags.liveness_check_api&quot;)"
        errorLine2="                ~~~~~~~~~~~~~~~~~~~~~~~~~~~~~~~~~~~~~~~~~~~~">
        <location
            file="packages/modules/IPsec/src/java/android/net/ipsec/ike/IkeSessionCallback.java"
            line="82"
            column="17"/>
    </issue>

    <issue
        id="FlaggedApi"
        message="@FlaggedApi should specify an actual flag constant; raw strings are discouraged (and more importantly, **not enforced**)"
        errorLine1="    @FlaggedApi(&quot;com.android.ipsec.flags.liveness_check_api&quot;)"
        errorLine2="                ~~~~~~~~~~~~~~~~~~~~~~~~~~~~~~~~~~~~~~~~~~~~">
        <location
            file="packages/modules/IPsec/src/java/android/net/ipsec/ike/IkeSessionCallback.java"
            line="94"
            column="17"/>
    </issue>

    <issue
        id="FlaggedApi"
        message="@FlaggedApi should specify an actual flag constant; raw strings are discouraged (and more importantly, **not enforced**)"
        errorLine1="    @FlaggedApi(&quot;com.android.ipsec.flags.liveness_check_api&quot;)"
        errorLine2="                ~~~~~~~~~~~~~~~~~~~~~~~~~~~~~~~~~~~~~~~~~~~~">
        <location
            file="packages/modules/IPsec/src/java/android/net/ipsec/ike/IkeSessionCallback.java"
            line="94"
            column="17"/>
    </issue>

    <issue
        id="FlaggedApi"
        message="@FlaggedApi should specify an actual flag constant; raw strings are discouraged (and more importantly, **not enforced**)"
        errorLine1="    @FlaggedApi(&quot;com.android.ipsec.flags.liveness_check_api&quot;)"
        errorLine2="                ~~~~~~~~~~~~~~~~~~~~~~~~~~~~~~~~~~~~~~~~~~~~">
        <location
            file="packages/modules/IPsec/src/java/android/net/ipsec/ike/IkeSessionCallback.java"
            line="94"
            column="17"/>
    </issue>

    <issue
        id="FlaggedApi"
        message="@FlaggedApi should specify an actual flag constant; raw strings are discouraged (and more importantly, **not enforced**)"
        errorLine1="    @FlaggedApi(&quot;com.android.ipsec.flags.liveness_check_api&quot;)"
        errorLine2="                ~~~~~~~~~~~~~~~~~~~~~~~~~~~~~~~~~~~~~~~~~~~~">
        <location
            file="packages/modules/IPsec/src/java/android/net/ipsec/ike/IkeSessionCallback.java"
            line="94"
            column="17"/>
    </issue>

    <issue
        id="FlaggedApi"
        message="@FlaggedApi should specify an actual flag constant; raw strings are discouraged (and more importantly, **not enforced**)"
        errorLine1="    @FlaggedApi(&quot;com.android.ipsec.flags.liveness_check_api&quot;)"
        errorLine2="                ~~~~~~~~~~~~~~~~~~~~~~~~~~~~~~~~~~~~~~~~~~~~">
        <location
            file="packages/modules/IPsec/src/java/android/net/ipsec/ike/IkeSessionCallback.java"
            line="111"
            column="17"/>
    </issue>

    <issue
        id="FlaggedApi"
        message="@FlaggedApi should specify an actual flag constant; raw strings are discouraged (and more importantly, **not enforced**)"
        errorLine1="    @FlaggedApi(&quot;com.android.ipsec.flags.liveness_check_api&quot;)"
        errorLine2="                ~~~~~~~~~~~~~~~~~~~~~~~~~~~~~~~~~~~~~~~~~~~~">
        <location
            file="packages/modules/IPsec/src/java/android/net/ipsec/ike/IkeSessionCallback.java"
            line="111"
            column="17"/>
    </issue>

    <issue
        id="FlaggedApi"
        message="@FlaggedApi should specify an actual flag constant; raw strings are discouraged (and more importantly, **not enforced**)"
        errorLine1="    @FlaggedApi(&quot;com.android.ipsec.flags.liveness_check_api&quot;)"
        errorLine2="                ~~~~~~~~~~~~~~~~~~~~~~~~~~~~~~~~~~~~~~~~~~~~">
        <location
            file="packages/modules/IPsec/src/java/android/net/ipsec/ike/IkeSessionCallback.java"
            line="111"
            column="17"/>
    </issue>

    <issue
        id="FlaggedApi"
        message="@FlaggedApi should specify an actual flag constant; raw strings are discouraged (and more importantly, **not enforced**)"
        errorLine1="    @FlaggedApi(&quot;com.android.ipsec.flags.liveness_check_api&quot;)"
        errorLine2="                ~~~~~~~~~~~~~~~~~~~~~~~~~~~~~~~~~~~~~~~~~~~~">
        <location
            file="packages/modules/IPsec/src/java/android/net/ipsec/ike/IkeSessionCallback.java"
            line="111"
            column="17"/>
    </issue>

    <issue
        id="FlaggedApi"
        message="@FlaggedApi should specify an actual flag constant; raw strings are discouraged (and more importantly, **not enforced**)"
        errorLine1="    @FlaggedApi(&quot;com.android.ipsec.flags.liveness_check_api&quot;)"
        errorLine2="                ~~~~~~~~~~~~~~~~~~~~~~~~~~~~~~~~~~~~~~~~~~~~">
        <location
            file="packages/modules/IPsec/src/java/android/net/ipsec/ike/IkeSessionCallback.java"
            line="325"
            column="17"/>
    </issue>

    <issue
        id="FlaggedApi"
        message="@FlaggedApi should specify an actual flag constant; raw strings are discouraged (and more importantly, **not enforced**)"
        errorLine1="    @FlaggedApi(&quot;com.android.ipsec.flags.liveness_check_api&quot;)"
        errorLine2="                ~~~~~~~~~~~~~~~~~~~~~~~~~~~~~~~~~~~~~~~~~~~~">
        <location
            file="packages/modules/IPsec/src/java/android/net/ipsec/ike/IkeSessionCallback.java"
            line="325"
            column="17"/>
    </issue>

    <issue
        id="FlaggedApi"
        message="@FlaggedApi should specify an actual flag constant; raw strings are discouraged (and more importantly, **not enforced**)"
        errorLine1="    @FlaggedApi(&quot;com.android.ipsec.flags.dpd_disable_api&quot;)"
        errorLine2="                ~~~~~~~~~~~~~~~~~~~~~~~~~~~~~~~~~~~~~~~~~">
        <location
            file="packages/modules/IPsec/src/java/android/net/ipsec/ike/IkeSessionParams.java"
            line="373"
            column="17"/>
    </issue>

    <issue
        id="FlaggedApi"
        message="@FlaggedApi should specify an actual flag constant; raw strings are discouraged (and more importantly, **not enforced**)"
        errorLine1="    @FlaggedApi(&quot;com.android.ipsec.flags.dpd_disable_api&quot;)"
        errorLine2="                ~~~~~~~~~~~~~~~~~~~~~~~~~~~~~~~~~~~~~~~~~">
        <location
            file="packages/modules/IPsec/src/java/android/net/ipsec/ike/IkeSessionParams.java"
            line="373"
            column="17"/>
    </issue>

    <issue
        id="FlaggedApi"
        message="@FlaggedApi should specify an actual flag constant; raw strings are discouraged (and more importantly, **not enforced**)"
        errorLine1="    @FlaggedApi(&quot;com.android.ipsec.flags.liveness_check_api&quot;)"
        errorLine2="                ~~~~~~~~~~~~~~~~~~~~~~~~~~~~~~~~~~~~~~~~~~~~">
        <location
            file="packages/modules/IPsec/src/java/android/net/ipsec/ike/IkeSessionParams.java"
            line="876"
            column="17"/>
    </issue>

    <issue
        id="FlaggedApi"
        message="@FlaggedApi should specify an actual flag constant; raw strings are discouraged (and more importantly, **not enforced**)"
        errorLine1="    @FlaggedApi(&quot;com.android.ipsec.flags.liveness_check_api&quot;)"
        errorLine2="                ~~~~~~~~~~~~~~~~~~~~~~~~~~~~~~~~~~~~~~~~~~~~">
        <location
            file="packages/modules/IPsec/src/java/android/net/ipsec/ike/IkeSessionParams.java"
            line="876"
            column="17"/>
    </issue>

    <issue
        id="FlaggedApi"
        message="@FlaggedApi should specify an actual flag constant; raw strings are discouraged (and more importantly, **not enforced**)"
        errorLine1="    @FlaggedApi(&quot;com.android.ipsec.flags.enabled_ike_options_api&quot;)"
        errorLine2="                ~~~~~~~~~~~~~~~~~~~~~~~~~~~~~~~~~~~~~~~~~~~~~~~~~">
        <location
            file="packages/modules/IPsec/src/java/android/net/ipsec/ike/IkeSessionParams.java"
            line="914"
            column="17"/>
    </issue>

    <issue
        id="FlaggedApi"
        message="@FlaggedApi should specify an actual flag constant; raw strings are discouraged (and more importantly, **not enforced**)"
        errorLine1="        @FlaggedApi(&quot;com.android.ipsec.flags.liveness_check_api&quot;)"
        errorLine2="                    ~~~~~~~~~~~~~~~~~~~~~~~~~~~~~~~~~~~~~~~~~~~~">
        <location
            file="packages/modules/IPsec/src/java/android/net/ipsec/ike/IkeSessionParams.java"
            line="2185"
            column="21"/>
    </issue>

    <issue
        id="FlaggedApi"
        message="@FlaggedApi should specify an actual flag constant; raw strings are discouraged (and more importantly, **not enforced**)"
        errorLine1="        @FlaggedApi(&quot;com.android.ipsec.flags.liveness_check_api&quot;)"
        errorLine2="                    ~~~~~~~~~~~~~~~~~~~~~~~~~~~~~~~~~~~~~~~~~~~~">
        <location
            file="packages/modules/IPsec/src/java/android/net/ipsec/ike/IkeSessionParams.java"
            line="2185"
            column="21"/>
    </issue>

</issues>